{"orderId": "726213314088015", "areaId": "24", "siteList": [{"nodeId": "LM1", "nodeType": "LM", "postionX": 0.0, "postionY": 0.0, "nodeTime": 0}, {"nodeId": "LM8", "nodeType": "LM", "postionX": 0.0, "postionY": 0.0, "nodeTime": 1}], "simulation": false},
{"orderId": "726213333102030", "areaId": "24", "siteList": [{"nodeId": "LM1", "nodeType": "LM", "postionX": 0.0, "postionY": 0.0, "nodeTime": 0}, {"nodeId": "LM8", "nodeType": "LM", "postionX": 0.0, "postionY": 0.0, "nodeTime": 1}], "simulation": false},
{"orderId": "726213904940029", "areaId": "24", "siteList": [{"nodeId": "LM1", "nodeType": "LM", "postionX": 0.0, "postionY": 0.0, "nodeTime": 0}, {"nodeId": "LM8", "nodeType": "LM", "postionX": 0.0, "postionY": 0.0, "nodeTime": 1}], "simulation": false},
{"orderId": "726213954569048", "areaId": "24", "siteList": [{"nodeId": "LM1", "nodeType": "LM", "postionX": 0.0, "postionY": 0.0, "nodeTime": 0}, {"nodeId": "LM8", "nodeType": "LM", "postionX": 0.0, "postionY": 0.0, "nodeTime": 1}], "simulation": false},
